{"title":"인터파크 티켓 모바일","url":"http://mticket.interpark.com/Notice/Index?Genre=&Page=1&PageSize=10&Sort=1","favicon":"http://mticket.interpark.com/Notice/favicon.ico","elements":[{"title":"폴킴 공식 팬클럽 〈폴인럽’23〉 모집 티켓오픈 안내","contents":"2022.10.26\n                                    <span>20:00</span>","link":"http://mticket.interpark.com/Notice/NoticeView?bn=34&no=44759","retrieved":1666620466666},{"title":"2022-23 이무진 전국투어 콘서트 [별책부록] - 대구 티켓오픈 안내","contents":"2022.10.31\n                                    <span>20:00</span>","link":"http://mticket.interpark.com/Notice/NoticeView?bn=34&no=44758","retrieved":1666620466674},{"title":"모아기타앙상블 정기연주회 티켓오픈 안내","contents":"2022.10.26\n                                    <span>09:00</span>","link":"http://mticket.interpark.com/Notice/NoticeView?bn=34&no=44757","retrieved":1666620466675},{"title":"첼로투첼로 콘서트 티켓오픈 안내","contents":"2022.10.27\n                                    <span>12:00</span>","link":"http://mticket.interpark.com/Notice/NoticeView?bn=34&no=44756","retrieved":1666620466678},{"title":"앙드레 브라질리에 티켓오픈 안내","contents":"2022.10.25\n                                    <span>09:00</span>","link":"http://mticket.interpark.com/Notice/NoticeView?bn=53&no=927","retrieved":1666620466682},{"title":"뮤지컬 <서편제> - 대구 티켓오픈 안내","contents":"2022.10.26\n                                    <span>11:00</span>","link":"http://mticket.interpark.com/Notice/NoticeView?bn=34&no=44755","retrieved":1666620466683},{"title":"오페레타 뮤지컬 판타지아 시즌2 - 특명! 음치 대마왕으로부터 엄마를 구하라! 티켓오픈 안내","contents":"2022.10.27\n                                    <span>14:00</span>","link":"http://mticket.interpark.com/Notice/NoticeView?bn=34&no=44754","retrieved":1666620466684},{"title":"2022 트롯 전국체전 TOP8 콘서트 - 서울 티켓오픈 안내","contents":"2022.11.01\n                                    <span>14:00</span>","link":"http://mticket.interpark.com/Notice/NoticeView?bn=34&no=44753","retrieved":1666620466686},{"title":"뮤지컬 〈테레즈 라캥〉 마지막 티켓오픈 안내","contents":"2022.10.27\n                                    <span>11:00</span>","link":"http://mticket.interpark.com/Notice/NoticeView?bn=34&no=44752","retrieved":1666620466689},{"title":"손열음의 커튼콜 추가티켓오픈 안내","contents":"2022.10.26\n                                    <span>14:00</span>","link":"http://mticket.interpark.com/Notice/NoticeView?bn=34&no=44751","retrieved":1666620466696}]}